plume_api/__init__.py
plume_api/main.py
plume_api-1.1.2.dist-info/LICENSE
plume_api-1.1.2.dist-info/METADATA
plume_api-1.1.2.dist-info/WHEEL
plume_api-1.1.2.dist-info/RECORD
