Metadata-Version: 2.3
Name: plume-api
Version: 1.1.2
Summary: Unofficial Plume API Wrapper
License: MIT
Author: Awakno
Author-email: contact@awakno.fr
Requires-Python: >=3.8.1,<4.0.0
Classifier: License :: OSI Approved :: MIT License
Classifier: Programming Language :: Python :: 3
Classifier: Programming Language :: Python :: 3.9
Classifier: Programming Language :: Python :: 3.10
Classifier: Programming Language :: Python :: 3.11
Classifier: Programming Language :: Python :: 3.12
Classifier: Programming Language :: Python :: 3.13
Requires-Dist: requests (>=2.32.3,<3.0.0)
Project-URL: Homepage, https://plume.ptarmigan.xyz/
Project-URL: Repository, https://github.com/Awakno/plume-api.py
